freight_analytics/__init__.py
freight_analytics/app.py
freight_analytics/cli.py
freight_analytics/dashboard.py
freight_analytics/data/Rail_Carloadings_originated.csv
freight_analytics/data/__init__.py
freight_analytics/data/port_dataset.json
freight_analytics_dashboard-1.0.0.dist-info/licenses/LICENSE
freight_analytics_dashboard-1.0.0.dist-info/METADATA
freight_analytics_dashboard-1.0.0.dist-info/WHEEL
freight_analytics_dashboard-1.0.0.dist-info/entry_points.txt
freight_analytics_dashboard-1.0.0.dist-info/top_level.txt
freight_analytics_dashboard-1.0.0.dist-info/RECORD
