Metadata-Version: 2.4
Name: freight-analytics-dashboard
Version: 1.0.0
Summary: Advanced US Freight Analytics Dashboard with Interactive Visualizations
Home-page: https://github.com/meghkc/DashBoard
Author: Megh KC
Author-email: Megh KC <kc.megh2048@gmail.com>
License: MIT
Project-URL: Homepage, https://github.com/meghkc/DashBoard
Project-URL: Repository, https://github.com/meghkc/DashBoard
Project-URL: Issues, https://github.com/meghkc/DashBoard/issues
Project-URL: Documentation, https://github.com/meghkc/DashBoard/blob/main/README.md
Keywords: freight,analytics,dashboard,visualization,streamlit,logistics
Classifier: Development Status :: 5 - Production/Stable
Classifier: Intended Audience :: Developers
Classifier: Intended Audience :: Science/Research
Classifier: Topic :: Scientific/Engineering :: Visualization
Classifier: License :: OSI Approved :: MIT License
Classifier: Programming Language :: Python :: 3
Classifier: Programming Language :: Python :: 3.8
Classifier: Programming Language :: Python :: 3.9
Classifier: Programming Language :: Python :: 3.10
Classifier: Programming Language :: Python :: 3.11
Classifier: Programming Language :: Python :: 3.12
Requires-Python: >=3.8
License-File: LICENSE
Requires-Dist: streamlit>=1.28.0
Requires-Dist: pandas>=1.5.0
Requires-Dist: plotly>=5.0.0
Requires-Dist: matplotlib>=3.5.0
Requires-Dist: numpy>=1.21.0
Provides-Extra: dev
Requires-Dist: pytest>=6.0; extra == "dev"
Requires-Dist: black>=21.0; extra == "dev"
Requires-Dist: flake8>=3.8; extra == "dev"
Dynamic: author
Dynamic: home-page
Dynamic: license-file
Dynamic: requires-python
